sphinx_last_updated_by_git.py
sphinx_last_updated_by_git-0.3.8.dist-info/LICENSE
sphinx_last_updated_by_git-0.3.8.dist-info/METADATA
sphinx_last_updated_by_git-0.3.8.dist-info/WHEEL
sphinx_last_updated_by_git-0.3.8.dist-info/top_level.txt
sphinx_last_updated_by_git-0.3.8.dist-info/zip-safe
sphinx_last_updated_by_git-0.3.8.dist-info/RECORD
