Metadata-Version: 2.1
Name: sphinx-last-updated-by-git
Version: 0.3.8
Summary: Get the "last updated" time for each Sphinx page from Git
Home-page: https://github.com/mgeier/sphinx-last-updated-by-git/
Author: Matthias Geier
Author-email: Matthias.Geier@gmail.com
License: BSD-2-Clause
Keywords: Sphinx,Git
Platform: any
Classifier: Framework :: Sphinx
Classifier: Framework :: Sphinx :: Extension
Classifier: License :: OSI Approved :: BSD License
Classifier: Operating System :: OS Independent
Classifier: Programming Language :: Python
Classifier: Programming Language :: Python :: 3
Classifier: Topic :: Documentation :: Sphinx
Requires-Python: >=3.7
License-File: LICENSE
Requires-Dist: sphinx>=1.8
